Metadata-Version: 2.1
Name: kemem
Version: 2.0.5
Summary: A Secure and Powerful Python-Pyrogram Based Library For Naya-Pyro.
Home-page: https://github.com/opet321/pusing
Author: melisa212
Author-email: opetbae6@gmail.com
License: GNU AFFERO GENERAL PUBLIC LICENSE (v3)
Project-URL: Bug Tracker, https://github.com/opet321/pusing/issues
Project-URL: Documentation, https://t.me/lpm_linux
Project-URL: Source Code, https://github.com/opet321/pusing
Platform: UNKNOWN
Classifier: Programming Language :: Python :: 3
Classifier: Programming Language :: Python :: 3.8
Classifier: Programming Language :: Python :: 3.9
Classifier: Programming Language :: Python :: 3.10
Classifier: Programming Language :: Python :: 3.11
Classifier: Programming Language :: Python :: 3.12
Classifier: License :: OSI Approved :: GNU General Public License v3 (GPLv3)
Classifier: Operating System :: OS Independent
Requires-Python: >3.7, <3.12
